LICENSE.txt
MANIFEST.in
README.rst
requirements.txt
setup.py
chatpy/__init__.py
chatpy/api.py
chatpy/auth.py
chatpy/binder.py
chatpy/cache.py
chatpy/error.py
chatpy/models.py
chatpy/parsers.py
chatpy/utils.py
chatpy.egg-info/PKG-INFO
chatpy.egg-info/SOURCES.txt
chatpy.egg-info/dependency_links.txt
chatpy.egg-info/requires.txt
chatpy.egg-info/top_level.txt
chatpy.egg-info/zip-safe
examples/get_messages.py