Metadata-Version: 1.1
Name: chatpy
Version: 0.2.1
Summary: Chatwork API for Python
Home-page: https://github.com/aqn/chatpy
Author: aqn
Author-email: aqn000 at gmail.com
License: MIT
Keywords: chatwork library
Platform: UNKNOWN
Classifier: Development Status :: 3 - Alpha
Classifier: Topic :: Software Development :: Libraries
Classifier: License :: OSI Approved :: MIT License
Classifier: Operating System :: OS Independent
Classifier: Programming Language :: Python
Classifier: Programming Language :: Python :: 2
Classifier: Programming Language :: Python :: 2.6
Classifier: Programming Language :: Python :: 2.7
